pygnosis/__init__.py
pygnosis/composed_indicator.py
pygnosis/health.py
pygnosis/indicator.py
pygnosis/status.py
pygnosis-0.1.2.dist-info/METADATA
pygnosis-0.1.2.dist-info/WHEEL
pygnosis-0.1.2.dist-info/licenses/LICENSE
pygnosis-0.1.2.dist-info/RECORD
