Metadata-Version: 2.4
Name: pygnosis
Version: 0.1.2
Summary: A modern, composable health monitoring library for Python applications with hierarchical status aggregation, async support, and flexible configuration system.
Project-URL: Homepage, https://github.com/javamaker-python/pygnosis
Project-URL: Repository, https://github.com/javamaker-python/pygnosis.git
Project-URL: Bug Tracker, https://github.com/javamaker-python/pygnosis/issues
Project-URL: Changelog, https://github.com/javamaker-python/pygnosis/blob/main/CHANGELOG.md
Author-email: Ilya Yushin <ilya.yushin@gmail.com>
Maintainer-email: Ilya Yushin <ilya.yushin@gmail.com>
License: MIT License
License-File: LICENSE
Keywords: check,health,microservices,monitoring,status
Classifier: Development Status :: 4 - Beta
Classifier: Intended Audience :: Developers
Classifier: License :: OSI Approved :: MIT License
Classifier: Operating System :: OS Independent
Classifier: Programming Language :: Python :: 3
Classifier: Programming Language :: Python :: 3.11
Classifier: Topic :: Software Development :: Libraries :: Python Modules
Classifier: Topic :: System :: Monitoring
Classifier: Typing :: Typed
Requires-Python: >=3.11
Requires-Dist: pydantic>=2.0.0
